[
	{
	"Name": "vsync",
	"Category": "Graphics",
	"TriggerValue": true,
	"RelationActions": [
	  {
		"Name": "setting_framerate_cap",
		"Category": "Graphics",
		"ActionType": "Disable"
	  },
	  {
		"Name": "setting_framerate_cap",
		"Category": "Graphics",
		"ActionType": "ForceSet",
		"Value": "off"
	  }
	]
	},
	{
	"Name": "upscale",
	"Category": "Graphics",
	"TriggerValue": "dlss",
	"RelationActions": [
	  {
		"Name": "anti_aliasing",
		"Category": "Graphics",
		"ActionType": "Disable"
	  },
	  {
		"Name": "anti_aliasing",
		"Category": "Graphics",
		"ActionType": "ForceSet",
		"Value": "DISABLED"
	  }
	]
	},
	{
	"Name": "music_system_type",
	"Category": "Audio",
	"TriggerValue": "mus_systemType_dynamic_all",
	"RelationActions": [
	  {
		"Name": "volume.vca:/MUSIC_INTENSITY",
		"Category": "Audio",
		"ActionType": "Disable"
	  }
	]
	},
	{
	"Name": "music_system_type",
	"Category": "Audio",
	"TriggerValue": "mus_systemType_dynamic_cinematic",
	"RelationActions": [
	  {
		"Name": "volume.vca:/MUSIC_INTENSITY",
		"Category": "Audio",
		"ActionType": "Disable"
	  }
	]
	},
	{
	"Name": "music_system_type",
	"Category": "Audio",
	"TriggerValue": "mus_systemType_dynamic_cultural",
	"RelationActions": [
	  {
		"Name": "volume.vca:/MUSIC_INTENSITY",
		"Category": "Audio",
		"ActionType": "Disable"
	  }
	]
	},
	{
	"Name": "music_system_type",
	"Category": "Audio",
	"TriggerValue": "mus_systemType_nomusic",
	"RelationActions": [
	  {
		"Name": "volume.vca:/MUSIC_INTENSITY",
		"Category": "Audio",
		"ActionType": "Disable"
	  }
	]
	}
]
